xconvey/__init__.py
xconvey/xconvey.py
pop_xconvey-1.0.0.dist-info/METADATA
pop_xconvey-1.0.0.dist-info/WHEEL
pop_xconvey-1.0.0.dist-info/top_level.txt
pop_xconvey-1.0.0.dist-info/RECORD
